COPYING
README
pyproject.toml
setup.cfg
bin/n23-db
bin/n23-db-sync
bin/n23-run
n23/__init__.py
n23/error.py
n23/fn.py
n23/pipeline.hy
n23/pipeline.pyi
n23/py.typed
n23/queue.py
n23/scheduler.py
n23/sink.py
n23/timer.py
n23/util.py
n23.egg-info/PKG-INFO
n23.egg-info/SOURCES.txt
n23.egg-info/dependency_links.txt
n23.egg-info/requires.txt
n23.egg-info/top_level.txt
n23/app/__init__.py
n23/app/config.py
n23/app/config_schema.hy
n23/app/config_schema.pyi
n23/app/core.py
n23/app/op.hy
n23/app/op.pyi
n23/app/runner.hy
n23/app/runner.pyi
n23/app/types.py
n23/dsl/__init__.py
n23/dsl/parser.py
n23/storage/__init__.py
n23/storage/api.py
n23/storage/config/__init__.py
n23/storage/config/reader.py
n23/storage/config/schema.hy
n23/storage/config/schema.pyi
n23/storage/config/types.py
n23/storage/pg/__init__.py
n23/storage/pg/core.py
tests/test_fn.py
tests/test_queue.py
tests/test_scheduler.py
tests/test_timer.py
tests/test_util.py