Metadata-Version: 2.1
Name: n23
Version: 0.9.0
Summary: n23 - data acquisition and processing framework
Home-page: https://gitlab.com/n23/n23
Author: Artur Wroblewski
Author-email: wrobell@riseup.net
License: GPLv3+
Project-URL: Code, https://gitlab.com/n23/n23
Project-URL: Bug tracker, https://gitlab.com/n23/n23/issues
Classifier: Topic :: Software Development :: Libraries
Classifier: License :: OSI Approved :: GNU General Public License v3 or later (GPLv3+)
Classifier: Programming Language :: Python :: 3
Classifier: Development Status :: 3 - Alpha
Requires-Python: >=3.12
License-File: COPYING
Requires-Dist: asyncpg>=0.24.0
Requires-Dist: atimer>=1.2.0
Requires-Dist: hy>=1.0.0
Requires-Dist: hyrule>=0.7.0
Requires-Dist: uvloop>=0.19.0
Provides-Extra: tests
Requires-Dist: mypy==1.11.2; extra == "tests"
Requires-Dist: pytest-cov; extra == "tests"
Requires-Dist: pytest-timeout; extra == "tests"
Requires-Dist: pytest-asyncio; extra == "tests"
Requires-Dist: pytest-mock; extra == "tests"
Requires-Dist: ruff>=0.6.7; extra == "tests"
